amtm_signaldetect/__init__.py
amtm_signaldetect/aMTMSignalDetect.py
amtm_signaldetect-1.0.5.dist-info/LICENSE
amtm_signaldetect-1.0.5.dist-info/METADATA
amtm_signaldetect-1.0.5.dist-info/WHEEL
amtm_signaldetect-1.0.5.dist-info/top_level.txt
amtm_signaldetect-1.0.5.dist-info/RECORD
