Metadata-Version: 2.1
Name: amtm_signaldetect
Version: 1.0.5
Summary: Periodic Signal Detection via the Adaptive Multitaper Method (aMTM)
Home-page: https://github.com/hsalinasGIT/amtm_signaldetect
Author: Hector A Salinas
Author-email: has4551@mavs.uta.edu
License: MIT
Keywords: periodic signal detection
Classifier: Development Status :: 5 - Production/Stable
Classifier: License :: OSI Approved :: MIT License
Classifier: Programming Language :: Python :: 3
Classifier: Programming Language :: Python :: 3.6
Classifier: Programming Language :: Python :: 3.7
Classifier: Programming Language :: Python :: 3.8
Classifier: Operating System :: OS Independent
License-File: LICENSE
Requires-Dist: multitaper
Requires-Dist: scipy
Requires-Dist: numpy
Requires-Dist: matplotlib
